evo_featureflags_client-0.7.0.dist-info/METADATA
evo_featureflags_client-0.7.0.dist-info/WHEEL
evo_featureflags_client-0.7.0.dist-info/entry_points.txt
examples/README.md
examples/__init__.py
examples/http/__init__.py
examples/http/aiohttp_client.py
examples/http/config.py
examples/http/dummy_async_client.py
examples/http/dummy_sync_client.py
examples/http/flags.py
examples/http/httpx_client.py
examples/http/requests_client.py
featureflags_client/__init__.py
featureflags_client/http/__init__.py
featureflags_client/http/client.py
featureflags_client/http/conditions.py
featureflags_client/http/constants.py
featureflags_client/http/flags.py
featureflags_client/http/managers/__init__.py
featureflags_client/http/managers/aiohttp.py
featureflags_client/http/managers/base.py
featureflags_client/http/managers/dummy.py
featureflags_client/http/managers/httpx.py
featureflags_client/http/managers/requests.py
featureflags_client/http/state.py
featureflags_client/http/types.py
featureflags_client/http/utils.py
featureflags_client/http/values.py
featureflags_client/tests/__init__.py
featureflags_client/tests/conftest.py
featureflags_client/tests/http/__init__.py
featureflags_client/tests/http/managers/__init__.py
featureflags_client/tests/http/managers/test_async.py
featureflags_client/tests/http/managers/test_dummy.py
featureflags_client/tests/http/managers/test_sync.py
featureflags_client/tests/http/test_conditions.py
featureflags_client/tests/http/test_utils.py
evo_featureflags_client-0.7.0.dist-info/RECORD
