Metadata-Version: 2.1
Name: evo-featureflags-client
Version: 0.7.0
Summary: Feature flags client
Author-Email: "d.zakharchuk" <d.zakharchuk@smartweb.com.ua>, "m.kindritskiy" <m.kindritskiy@smartweb.com.ua>, Vladimir Magamedov <vladimir@magamedov.com>
License: MIT
Requires-Python: >=3.9
Requires-Dist: dataclass-wizard~=0.26
Provides-Extra: httpx
Requires-Dist: httpx~=0.25; extra == "httpx"
Provides-Extra: aiohttp
Requires-Dist: aiohttp~=3.10; extra == "aiohttp"
Provides-Extra: requests
Requires-Dist: requests~=2.32; extra == "requests"
